omnibase_infra/__init__.py
omnibase_infra/adapters/adapter_onex_tool_execution.py
omnibase_infra/capabilities/__init__.py
omnibase_infra/capabilities/capability_inference_rules.py
omnibase_infra/capabilities/contract_capability_extractor.py
omnibase_infra/capabilities/intent_type_extractor.py
omnibase_infra/cli/__init__.py
omnibase_infra/cli/commands.py
omnibase_infra/clients/__init__.py
omnibase_infra/configs/widget_mapping.yaml
omnibase_infra/constants_topic_patterns.py
omnibase_infra/contracts/handlers/filesystem/handler_contract.yaml
omnibase_infra/contracts/handlers/mcp/handler_contract.yaml
omnibase_infra/decorators/__init__.py
omnibase_infra/decorators/allow_any.py
omnibase_infra/dlq/__init__.py
omnibase_infra/dlq/constants_dlq.py
omnibase_infra/dlq/models/__init__.py
omnibase_infra/dlq/models/enum_replay_status.py
omnibase_infra/dlq/models/model_dlq_replay_record.py
omnibase_infra/dlq/models/model_dlq_tracking_config.py
omnibase_infra/dlq/service_dlq_tracking.py
omnibase_infra/enums/__init__.py
omnibase_infra/enums/enum_any_type_violation.py
omnibase_infra/enums/enum_backend_type.py
omnibase_infra/enums/enum_capture_outcome.py
omnibase_infra/enums/enum_capture_state.py
omnibase_infra/enums/enum_chain_violation_type.py
omnibase_infra/enums/enum_circuit_state.py
omnibase_infra/enums/enum_confirmation_event_type.py
omnibase_infra/enums/enum_consumer_group_purpose.py
omnibase_infra/enums/enum_contract_type.py
omnibase_infra/enums/enum_declarative_node_violation.py
omnibase_infra/enums/enum_dedupe_strategy.py
omnibase_infra/enums/enum_dispatch_status.py
omnibase_infra/enums/enum_environment.py
omnibase_infra/enums/enum_execution_shape_violation.py
omnibase_infra/enums/enum_handler_error_type.py
omnibase_infra/enums/enum_handler_loader_error.py
omnibase_infra/enums/enum_handler_source_mode.py
omnibase_infra/enums/enum_handler_source_type.py
omnibase_infra/enums/enum_handler_type.py
omnibase_infra/enums/enum_handler_type_category.py
omnibase_infra-0.2.9.dist-info/METADATA
omnibase_infra-0.2.9.dist-info/WHEEL
omnibase_infra-0.2.9.dist-info/entry_points.txt
omnibase_infra-0.2.9.dist-info/licenses/LICENSE
omnibase_infra-0.2.9.dist-info/RECORD
