Metadata-Version: 2.4
Name: omnibase_infra
Version: 0.2.9
Summary: ONEX Infrastructure - Service integration and database infrastructure tools
License: MIT
License-File: LICENSE
Author: OmniNode Team
Author-email: team@omninode.ai
Requires-Python: >=3.12,<4.0
Classifier: License :: OSI Approved :: MIT License
Classifier: Programming Language :: Python :: 3
Classifier: Programming Language :: Python :: 3.12
Classifier: Programming Language :: Python :: 3.13
Classifier: Programming Language :: Python :: 3.14
Requires-Dist: aiofiles (>=23.2.1,<24.0.0)
Requires-Dist: aiohttp (>=3.9.0,<4.0.0)
Requires-Dist: aiokafka (>=0.11.0,<0.12.0)
Requires-Dist: asyncpg (>=0.29.0,<0.30.0)
Requires-Dist: circuitbreaker (>=2.0.0,<3.0.0)
Requires-Dist: click (>=8.1.0,<9.0.0)
Requires-Dist: confluent-kafka (>=2.12.0,<3.0.0)
Requires-Dist: cryptography (>=46.0.3,<47.0.0)
Requires-Dist: dependency-injector (>=4.48.1,<5.0.0)
Requires-Dist: fastapi (>=0.120.1,<0.121.0)
Requires-Dist: httpx (>=0.28.1,<0.29.0)
Requires-Dist: hvac (>=2.1.0,<3.0.0)
Requires-Dist: jinja2 (>=3.1.6,<4.0.0)
Requires-Dist: jsonschema (>=4.20.0,<5.0.0)
Requires-Dist: mcp (>=1.25.0,<2.0.0)
Requires-Dist: neo4j (>=5.15.0,<6.0.0)
Requires-Dist: omnibase-core (>=0.11.0,<0.12.0)
Requires-Dist: omnibase-spi (>=0.6.4,<0.7.0)
Requires-Dist: opentelemetry-api (>=1.27.0,<2.0.0)
Requires-Dist: opentelemetry-exporter-otlp (>=1.27.0,<2.0.0)
Requires-Dist: opentelemetry-instrumentation (>=0.48b0,<0.49)
Requires-Dist: opentelemetry-instrumentation-aiohttp-client (>=0.48b0,<0.49)
Requires-Dist: opentelemetry-instrumentation-asyncpg (>=0.48b0,<0.49)
Requires-Dist: opentelemetry-instrumentation-fastapi (>=0.48b0,<0.49)
Requires-Dist: opentelemetry-instrumentation-kafka-python (>=0.48b0,<0.49)
Requires-Dist: opentelemetry-instrumentation-redis (>=0.48b0,<0.49)
Requires-Dist: opentelemetry-sdk (>=1.27.0,<2.0.0)
Requires-Dist: prometheus-client (>=0.19.0,<0.20.0)
Requires-Dist: psycopg2-binary (>=2.9.10,<3.0.0)
Requires-Dist: pydantic (>=2.11.7,<3.0.0)
Requires-Dist: pydantic-settings (>=2.2.1,<3.0.0)
Requires-Dist: python-consul (>=1.1.0,<2.0.0)
Requires-Dist: pyyaml (>=6.0.2,<7.0.0)
Requires-Dist: qdrant-client (>=1.12.0,<2.0.0)
Requires-Dist: redis (>=6.0.0,<7.0.0)
Requires-Dist: rich (>=13.7.0,<14.0.0)
Requires-Dist: slowapi (>=0.1.9,<0.2.0)
Requires-Dist: sqlparse (>=0.4.4,<0.5.0)
Requires-Dist: structlog (>=23.2.0,<24.0.0)
Requires-Dist: tenacity (>=9.0.0,<10.0.0)
Requires-Dist: uvicorn (>=0.32.0,<0.33.0)
